salnama/__init__.py
salnama/taghvim.py
salnama/taghvim_import.py
salnama/data/taghvim_db.csv
salnama-1.0.0.dist-info/LICENSE
salnama-1.0.0.dist-info/METADATA
salnama-1.0.0.dist-info/WHEEL
salnama-1.0.0.dist-info/top_level.txt
salnama-1.0.0.dist-info/RECORD
