Metadata-Version: 2.1
Name: salnama
Version: 1.0.0
Summary: taghvim is a Python(v3.x) library for Calendar and Date Convertor For Persian Date
Home-page: https://github.com/AbduEbrahimi/salnama
Author: AbduEbrahimi
Author-email: a.sanmarin@yahoo.com
License: UNKNOWN
Platform: UNKNOWN
Classifier: Programming Language :: Python :: 3
Classifier: License :: OSI Approved :: Apache Software License
